<?xml version="1.0" encoding="UTF-8" standalone="no"?><feature-model xmlns:xsi="http://www.w3.org/2001/XMLSchema-instance" xsi:noNamespaceSchemaLocation="http://www.tdg-seville.info/benavides/featuremodelling/feature-model.xsd"><feature name="_r"><binaryRelation name="0"><cardinality max="1" min="1"/><solitaryFeature name="_r_4"><binaryRelation name="1"><cardinality max="1" min="1"/><solitaryFeature name="_r_4_5"/></binaryRelation><binaryRelation name="2"><cardinality max="1" min="1"/><solitaryFeature name="_r_4_6"><binaryRelation name="3"><cardinality max="1" min="1"/><solitaryFeature name="_r_4_6_11"/></binaryRelation><binaryRelation name="4"><cardinality max="1" min="1"/><solitaryFeature name="_r_4_6_12"/></binaryRelation><binaryRelation name="5"><cardinality max="1" min="0"/><solitaryFeature name="_r_4_6_13"/></binaryRelation></solitaryFeature></binaryRelation></solitaryFeature></binaryRelation><binaryRelation name="6"><cardinality max="1" min="1"/><solitaryFeature name="_r_7"/></binaryRelation><binaryRelation name="7"><cardinality max="1" min="1"/><solitaryFeature name="_r_8"><binaryRelation name="8"><cardinality max="1" min="0"/><solitaryFeature name="_r_8_9"/></binaryRelation></solitaryFeature></binaryRelation><setRelation name="9"><cardinality max="2" min="1"/><groupedFeature name="_r_27_28"><binaryRelation name="10"><cardinality max="1" min="1"/><solitaryFeature name="_r_27_28_30"><setRelation name="11"><cardinality max="3" min="1"/><groupedFeature name="_r_27_28_30_22_23"/><groupedFeature name="_r_27_28_30_22_24"/><groupedFeature name="_r_27_28_30_22_25"/></setRelation></solitaryFeature></binaryRelation></groupedFeature><groupedFeature name="_r_27_29"/></setRelation></feature></feature-model>