<?xml version="1.0" encoding="UTF-8" standalone="no"?><feature-model xmlns:xsi="http://www.w3.org/2001/XMLSchema-instance" xsi:noNamespaceSchemaLocation="http://www.tdg-seville.info/benavides/featuremodelling/feature-model.xsd"><feature name="_r"><binaryRelation name="0"><cardinality max="1" min="1"/><solitaryFeature name="_r_1"><binaryRelation name="1"><cardinality max="1" min="1"/><solitaryFeature name="_r_1_2"><setRelation name="2"><cardinality max="1" min="1"/><groupedFeature name="_r_1_2_3_4"/><groupedFeature name="_r_1_2_3_13"/></setRelation></solitaryFeature></binaryRelation><binaryRelation name="3"><cardinality max="1" min="1"/><solitaryFeature name="_r_1_7"><setRelation name="4"><cardinality max="1" min="1"/><groupedFeature name="_r_1_7_9_10"/><groupedFeature name="_r_1_7_9_11"/><groupedFeature name="_r_1_7_9_12"/></setRelation></solitaryFeature></binaryRelation><binaryRelation name="5"><cardinality max="1" min="1"/><solitaryFeature name="_r_1_14"><setRelation name="6"><cardinality max="1" min="1"/><groupedFeature name="_r_1_14_19_20"/><groupedFeature name="_r_1_14_19_21"/><groupedFeature name="_r_1_14_19_22"/></setRelation></solitaryFeature></binaryRelation><binaryRelation name="7"><cardinality max="1" min="0"/><solitaryFeature name="_r_1_32"><setRelation name="8"><cardinality max="1" min="1"/><groupedFeature name="_r_1_32_33_34"/><groupedFeature name="_r_1_32_33_35"/></setRelation></solitaryFeature></binaryRelation><binaryRelation name="9"><cardinality max="1" min="1"/><solitaryFeature name="_r_1_36"><setRelation name="10"><cardinality max="1" min="1"/><groupedFeature name="_r_1_36_41_42"/><groupedFeature name="_r_1_36_41_43"/><groupedFeature name="_r_1_36_41_44"/></setRelation></solitaryFeature></binaryRelation></solitaryFeature></binaryRelation><binaryRelation name="11"><cardinality max="1" min="1"/><solitaryFeature name="_r_47"><binaryRelation name="12"><cardinality max="1" min="1"/><solitaryFeature name="_r_47_53"><binaryRelation name="13"><cardinality max="1" min="1"/><solitaryFeature name="_r_47_53_56"/></binaryRelation><binaryRelation name="14"><cardinality max="1" min="1"/><solitaryFeature name="_r_47_53_57"/></binaryRelation><binaryRelation name="15"><cardinality max="1" min="1"/><solitaryFeature name="_r_47_53_59"/></binaryRelation></solitaryFeature></binaryRelation><binaryRelation name="16"><cardinality max="1" min="0"/><solitaryFeature name="_r_47_54"><binaryRelation name="17"><cardinality max="1" min="0"/><solitaryFeature name="_r_47_54_60"/></binaryRelation><binaryRelation name="18"><cardinality max="1" min="0"/><solitaryFeature name="_r_47_54_61"/></binaryRelation><binaryRelation name="19"><cardinality max="1" min="1"/><solitaryFeature name="_r_47_54_62"/></binaryRelation><binaryRelation name="20"><cardinality max="1" min="0"/><solitaryFeature name="_r_47_54_63"/></binaryRelation><binaryRelation name="21"><cardinality max="1" min="0"/><solitaryFeature name="_r_47_54_64"/></binaryRelation><binaryRelation name="22"><cardinality max="1" min="0"/><solitaryFeature name="_r_47_54_65"/></binaryRelation><binaryRelation name="23"><cardinality max="1" min="0"/><solitaryFeature name="_r_47_54_66"/></binaryRelation></solitaryFeature></binaryRelation><binaryRelation name="24"><cardinality max="1" min="1"/><solitaryFeature name="_r_47_55"/></binaryRelation></solitaryFeature></binaryRelation><binaryRelation name="25"><cardinality max="1" min="1"/><solitaryFeature name="_r_48"><setRelation name="26"><cardinality max="7" min="1"/><groupedFeature name="_r_48_70_71"><binaryRelation name="27"><cardinality max="1" min="0"/><solitaryFeature name="_r_48_70_71_78"/></binaryRelation></groupedFeature><groupedFeature name="_r_48_70_72"><binaryRelation name="28"><cardinality max="1" min="0"/><solitaryFeature name="_r_48_70_72_79"/></binaryRelation><binaryRelation name="29"><cardinality max="1" min="0"/><solitaryFeature name="_r_48_70_72_80"/></binaryRelation><binaryRelation name="30"><cardinality max="1" min="0"/><solitaryFeature name="_r_48_70_72_81"/></binaryRelation><binaryRelation name="31"><cardinality max="1" min="0"/><solitaryFeature name="_r_48_70_72_82"/></binaryRelation><binaryRelation name="32"><cardinality max="1" min="0"/><solitaryFeature name="_r_48_70_72_83"/></binaryRelation></groupedFeature><groupedFeature name="_r_48_70_73"><setRelation name="33"><cardinality max="3" min="1"/><groupedFeature name="_r_48_70_73_84_85"/><groupedFeature name="_r_48_70_73_84_86"/><groupedFeature name="_r_48_70_73_84_87"/></setRelation></groupedFeature><groupedFeature name="_r_48_70_74"><binaryRelation name="34"><cardinality max="1" min="0"/><solitaryFeature name="_r_48_70_74_89"/></binaryRelation><binaryRelation name="35"><cardinality max="1" min="0"/><solitaryFeature name="_r_48_70_74_90"/></binaryRelation><binaryRelation name="36"><cardinality max="1" min="0"/><solitaryFeature name="_r_48_70_74_91"/></binaryRelation><binaryRelation name="37"><cardinality max="1" min="0"/><solitaryFeature name="_r_48_70_74_92"/></binaryRelation><binaryRelation name="38"><cardinality max="1" min="0"/><solitaryFeature name="_r_48_70_74_93"/></binaryRelation></groupedFeature><groupedFeature name="_r_48_70_75"><binaryRelation name="39"><cardinality max="1" min="0"/><solitaryFeature name="_r_48_70_75_94"/></binaryRelation><binaryRelation name="40"><cardinality max="1" min="0"/><solitaryFeature name="_r_48_70_75_95"/></binaryRelation><binaryRelation name="41"><cardinality max="1" min="0"/><solitaryFeature name="_r_48_70_75_96"/></binaryRelation></groupedFeature><groupedFeature name="_r_48_70_76"><binaryRelation name="42"><cardinality max="1" min="0"/><solitaryFeature name="_r_48_70_76_97"/></binaryRelation><binaryRelation name="43"><cardinality max="1" min="0"/><solitaryFeature name="_r_48_70_76_98"/></binaryRelation></groupedFeature><groupedFeature name="_r_48_70_77"/></setRelation></solitaryFeature></binaryRelation><binaryRelation name="44"><cardinality max="1" min="1"/><solitaryFeature name="_r_49"/></binaryRelation><binaryRelation name="45"><cardinality max="1" min="1"/><solitaryFeature name="_r_50"/></binaryRelation><binaryRelation name="46"><cardinality max="1" min="1"/><solitaryFeature name="_r_52"/></binaryRelation><binaryRelation name="47"><cardinality max="1" min="1"/><solitaryFeature name="_r_65"><binaryRelation name="48"><cardinality max="1" min="1"/><solitaryFeature name="_r_65_66"/></binaryRelation><binaryRelation name="49"><cardinality max="1" min="0"/><solitaryFeature name="_r_65_67"/></binaryRelation><setRelation name="50"><cardinality max="3" min="1"/><groupedFeature name="_r_65_68_69"/><groupedFeature name="_r_65_68_70"/><groupedFeature name="_r_65_68_72"/></setRelation><setRelation name="51"><cardinality max="1" min="1"/><groupedFeature name="_r_65_76_77"/><groupedFeature name="_r_65_76_78"/></setRelation></solitaryFeature></binaryRelation></feature></feature-model>