<?xml version="1.0" encoding="UTF-8" standalone="no"?><feature-model xmlns:xsi="http://www.w3.org/2001/XMLSchema-instance" xsi:noNamespaceSchemaLocation="http://www.tdg-seville.info/benavides/featuremodelling/feature-model.xsd"><feature name="_r"><binaryRelation name="0"><cardinality max="1" min="1"/><solitaryFeature name="_r_1"><setRelation name="1"><cardinality max="1" min="1"/><groupedFeature name="_r_1_5_6"><binaryRelation name="2"><cardinality max="1" min="1"/><solitaryFeature name="_r_1_5_6_9_10"/></binaryRelation></groupedFeature><groupedFeature name="_r_1_5_8"/></setRelation></solitaryFeature></binaryRelation><binaryRelation name="3"><cardinality max="1" min="1"/><solitaryFeature name="_r_2"><binaryRelation name="4"><cardinality max="1" min="0"/><solitaryFeature name="_r_2_16"><setRelation name="5"><cardinality max="1" min="1"/><groupedFeature name="_r_2_16_21_22"><setRelation name="6"><cardinality max="1" min="1"/><groupedFeature name="_r_2_16_21_22_24_25"/><groupedFeature name="_r_2_16_21_22_24_26"/></setRelation></groupedFeature><groupedFeature name="_r_2_16_21_23"/></setRelation></solitaryFeature></binaryRelation><binaryRelation name="7"><cardinality max="1" min="1"/><solitaryFeature name="_r_2_17"><setRelation name="8"><cardinality max="1" min="1"/><groupedFeature name="_r_2_17_27_28"/><groupedFeature name="_r_2_17_27_29"/></setRelation></solitaryFeature></binaryRelation></solitaryFeature></binaryRelation><binaryRelation name="9"><cardinality max="1" min="0"/><solitaryFeature name="_r_3"><setRelation name="10"><cardinality max="1" min="1"/><groupedFeature name="_r_3_30_31"/><groupedFeature name="_r_3_30_32"/></setRelation></solitaryFeature></binaryRelation><binaryRelation name="11"><cardinality max="1" min="1"/><solitaryFeature name="_r_4"><binaryRelation name="12"><cardinality max="1" min="1"/><solitaryFeature name="_r_4_35"><setRelation name="13"><cardinality max="1" min="1"/><groupedFeature name="_r_4_35_36_37"/><groupedFeature name="_r_4_35_36_38"/></setRelation></solitaryFeature></binaryRelation></solitaryFeature></binaryRelation><binaryRelation name="14"><cardinality max="1" min="0"/><solitaryFeature name="_r_40"><setRelation name="15"><cardinality max="1" min="1"/><groupedFeature name="_r_40_41_42"/><groupedFeature name="_r_40_41_43"/></setRelation></solitaryFeature></binaryRelation></feature><requires feature="_r_3_30_31" name="constraint_1" requires="_r_40_41_43"/><requires feature="_r_3_30_32" name="constraint_2" requires="_r_40_41_42"/></feature-model>