<?xml version="1.0" encoding="UTF-8" standalone="no"?><feature-model xmlns:xsi="http://www.w3.org/2001/XMLSchema-instance" xsi:noNamespaceSchemaLocation="http://www.tdg-seville.info/benavides/featuremodelling/feature-model.xsd"><feature name="_r"><binaryRelation name="0"><cardinality max="1" min="1"/><solitaryFeature name="_r_1"><binaryRelation name="1"><cardinality max="1" min="1"/><solitaryFeature name="_r_1_2"><binaryRelation name="2"><cardinality max="1" min="1"/><solitaryFeature name="_r_1_2_5"><setRelation name="3"><cardinality max="3" min="1"/><groupedFeature name="_r_1_2_5_8_9"><binaryRelation name="4"><cardinality max="1" min="1"/><solitaryFeature name="_r_1_2_5_8_9_16"><setRelation name="5"><cardinality max="9" min="1"/><groupedFeature name="_r_1_2_5_8_9_16_20_21"/><groupedFeature name="_r_1_2_5_8_9_16_20_27"/><groupedFeature name="_r_1_2_5_8_9_16_20_28"/><groupedFeature name="_r_1_2_5_8_9_16_20_29"/><groupedFeature name="_r_1_2_5_8_9_16_20_30"/><groupedFeature name="_r_1_2_5_8_9_16_20_31"/><groupedFeature name="_r_1_2_5_8_9_16_20_32"/><groupedFeature name="_r_1_2_5_8_9_16_20_33"/><groupedFeature name="_r_1_2_5_8_9_16_20_34"/></setRelation></solitaryFeature></binaryRelation><binaryRelation name="6"><cardinality max="1" min="1"/><solitaryFeature name="_r_1_2_5_8_9_17"><setRelation name="7"><cardinality max="3" min="1"/><groupedFeature name="_r_1_2_5_8_9_17_35_36"/><groupedFeature name="_r_1_2_5_8_9_17_35_37"/><groupedFeature name="_r_1_2_5_8_9_17_35_38"/></setRelation></solitaryFeature></binaryRelation><binaryRelation name="8"><cardinality max="1" min="1"/><solitaryFeature name="_r_1_2_5_8_9_18"><setRelation name="9"><cardinality max="2" min="1"/><groupedFeature name="_r_1_2_5_8_9_18_39_40"/><groupedFeature name="_r_1_2_5_8_9_18_39_41"/></setRelation></solitaryFeature></binaryRelation><binaryRelation name="10"><cardinality max="1" min="1"/><solitaryFeature name="_r_1_2_5_8_9_19"><setRelation name="11"><cardinality max="9" min="1"/><groupedFeature name="_r_1_2_5_8_9_19_42_43"/><groupedFeature name="_r_1_2_5_8_9_19_42_44"/><groupedFeature name="_r_1_2_5_8_9_19_42_45"/><groupedFeature name="_r_1_2_5_8_9_19_42_46"/><groupedFeature name="_r_1_2_5_8_9_19_42_47"/><groupedFeature name="_r_1_2_5_8_9_19_42_48"/><groupedFeature name="_r_1_2_5_8_9_19_42_49"/><groupedFeature name="_r_1_2_5_8_9_19_42_50"/><groupedFeature name="_r_1_2_5_8_9_19_42_51"/></setRelation></solitaryFeature></binaryRelation></groupedFeature><groupedFeature name="_r_1_2_5_8_25"><binaryRelation name="12"><cardinality max="1" min="1"/><solitaryFeature name="_r_1_2_5_8_25_52"><binaryRelation name="13"><cardinality max="1" min="1"/><solitaryFeature name="_r_1_2_5_8_25_52_53"/></binaryRelation></solitaryFeature></binaryRelation><binaryRelation name="14"><cardinality max="1" min="1"/><solitaryFeature name="_r_1_2_5_8_25_54"><binaryRelation name="15"><cardinality max="1" min="1"/><solitaryFeature name="_r_1_2_5_8_25_54_55"/></binaryRelation></solitaryFeature></binaryRelation><binaryRelation name="16"><cardinality max="1" min="1"/><solitaryFeature name="_r_1_2_5_8_25_56"><setRelation name="17"><cardinality max="9" min="1"/><groupedFeature name="_r_1_2_5_8_25_56_57_58"/><groupedFeature name="_r_1_2_5_8_25_56_57_59"/><groupedFeature name="_r_1_2_5_8_25_56_57_60"/><groupedFeature name="_r_1_2_5_8_25_56_57_61"/><groupedFeature name="_r_1_2_5_8_25_56_57_62"/><groupedFeature name="_r_1_2_5_8_25_56_57_63"/><groupedFeature name="_r_1_2_5_8_25_56_57_64"/><groupedFeature name="_r_1_2_5_8_25_56_57_65"/><groupedFeature name="_r_1_2_5_8_25_56_57_66"/></setRelation></solitaryFeature></binaryRelation><binaryRelation name="18"><cardinality max="1" min="1"/><solitaryFeature name="_r_1_2_5_8_25_67"><setRelation name="19"><cardinality max="1" min="1"/><groupedFeature name="_r_1_2_5_8_25_67_68_69"/><groupedFeature name="_r_1_2_5_8_25_67_68_70"/><groupedFeature name="_r_1_2_5_8_25_67_68_71"/><groupedFeature name="_r_1_2_5_8_25_67_68_72"/><groupedFeature name="_r_1_2_5_8_25_67_68_73"/></setRelation></solitaryFeature></binaryRelation></groupedFeature><groupedFeature name="_r_1_2_5_8_26"/></setRelation></solitaryFeature></binaryRelation></solitaryFeature></binaryRelation><binaryRelation name="20"><cardinality max="1" min="1"/><solitaryFeature name="_r_1_3"><binaryRelation name="21"><cardinality max="1" min="0"/><solitaryFeature name="_r_1_3_74"><binaryRelation name="22"><cardinality max="1" min="1"/><solitaryFeature name="_r_1_3_74_76"><binaryRelation name="23"><cardinality max="1" min="0"/><solitaryFeature name="_r_1_3_74_76_77"/></binaryRelation></solitaryFeature></binaryRelation></solitaryFeature></binaryRelation><binaryRelation name="24"><cardinality max="1" min="1"/><solitaryFeature name="_r_1_3_75"><binaryRelation name="25"><cardinality max="1" min="1"/><solitaryFeature name="_r_1_3_75_78"><binaryRelation name="26"><cardinality max="1" min="1"/><solitaryFeature name="_r_1_3_75_78_82"><setRelation name="27"><cardinality max="1" min="1"/><groupedFeature name="_r_1_3_75_78_82_83_84"/><groupedFeature name="_r_1_3_75_78_82_83_85"/><groupedFeature name="_r_1_3_75_78_82_83_86"/><groupedFeature name="_r_1_3_75_78_82_83_87"/></setRelation></solitaryFeature></binaryRelation></solitaryFeature></binaryRelation><binaryRelation name="28"><cardinality max="1" min="1"/><solitaryFeature name="_r_1_3_75_79"><binaryRelation name="29"><cardinality max="1" min="1"/><solitaryFeature name="_r_1_3_75_79_88"><setRelation name="30"><cardinality max="1" min="1"/><groupedFeature name="_r_1_3_75_79_88_89_90"/><groupedFeature name="_r_1_3_75_79_88_89_91"/></setRelation></solitaryFeature></binaryRelation></solitaryFeature></binaryRelation><binaryRelation name="31"><cardinality max="1" min="1"/><solitaryFeature name="_r_1_3_75_80"><binaryRelation name="32"><cardinality max="1" min="1"/><solitaryFeature name="_r_1_3_75_80_92"><setRelation name="33"><cardinality max="1" min="1"/><groupedFeature name="_r_1_3_75_80_92_95_96"/><groupedFeature name="_r_1_3_75_80_92_95_97"/><groupedFeature name="_r_1_3_75_80_92_95_98"/><groupedFeature name="_r_1_3_75_80_92_95_99"/></setRelation></solitaryFeature></binaryRelation><binaryRelation name="34"><cardinality max="1" min="1"/><solitaryFeature name="_r_1_3_75_80_93"><setRelation name="35"><cardinality max="1" min="1"/><groupedFeature name="_r_1_3_75_80_93_100_101"/><groupedFeature name="_r_1_3_75_80_93_100_102"/><groupedFeature name="_r_1_3_75_80_93_100_103"/><groupedFeature name="_r_1_3_75_80_93_100_104"/></setRelation></solitaryFeature></binaryRelation><binaryRelation name="36"><cardinality max="1" min="1"/><solitaryFeature name="_r_1_3_75_80_94"><binaryRelation name="37"><cardinality max="1" min="1"/><solitaryFeature name="_r_1_3_75_80_94_105"/></binaryRelation><binaryRelation name="38"><cardinality max="1" min="0"/><solitaryFeature name="_r_1_3_75_80_94_106"><setRelation name="39"><cardinality max="5" min="1"/><groupedFeature name="_r_1_3_75_80_94_106_107_108"/><groupedFeature name="_r_1_3_75_80_94_106_107_109"/><groupedFeature name="_r_1_3_75_80_94_106_107_110"/><groupedFeature name="_r_1_3_75_80_94_106_107_111"/><groupedFeature name="_r_1_3_75_80_94_106_107_112"/></setRelation></solitaryFeature></binaryRelation></solitaryFeature></binaryRelation></solitaryFeature></binaryRelation><binaryRelation name="40"><cardinality max="1" min="1"/><solitaryFeature name="_r_1_3_75_81"><setRelation name="41"><cardinality max="1" min="1"/><groupedFeature name="_r_1_3_75_81_113_114"/><groupedFeature name="_r_1_3_75_81_113_115"/><groupedFeature name="_r_1_3_75_81_113_116"/><groupedFeature name="_r_1_3_75_81_113_117"/><groupedFeature name="_r_1_3_75_81_113_118"/><groupedFeature name="_r_1_3_75_81_113_119"/></setRelation></solitaryFeature></binaryRelation></solitaryFeature></binaryRelation></solitaryFeature></binaryRelation><binaryRelation name="42"><cardinality max="1" min="1"/><solitaryFeature name="_r_1_4"><binaryRelation name="43"><cardinality max="1" min="1"/><solitaryFeature name="_r_1_4_120"><binaryRelation name="44"><cardinality max="1" min="1"/><solitaryFeature name="_r_1_4_120_123"><setRelation name="45"><cardinality max="1" min="1"/><groupedFeature name="_r_1_4_120_123_126_127"/><groupedFeature name="_r_1_4_120_123_126_128"/><groupedFeature name="_r_1_4_120_123_126_129"/><groupedFeature name="_r_1_4_120_123_126_130"/><groupedFeature name="_r_1_4_120_123_126_131"/></setRelation></solitaryFeature></binaryRelation><binaryRelation name="46"><cardinality max="1" min="1"/><solitaryFeature name="_r_1_4_120_124"><setRelation name="47"><cardinality max="1" min="1"/><groupedFeature name="_r_1_4_120_124_132_133"/><groupedFeature name="_r_1_4_120_124_132_134"/></setRelation></solitaryFeature></binaryRelation><binaryRelation name="48"><cardinality max="1" min="1"/><solitaryFeature name="_r_1_4_120_125"><setRelation name="49"><cardinality max="1" min="1"/><groupedFeature name="_r_1_4_120_125_135_136"/><groupedFeature name="_r_1_4_120_125_135_137"/><groupedFeature name="_r_1_4_120_125_135_138"/><groupedFeature name="_r_1_4_120_125_135_139"/><groupedFeature name="_r_1_4_120_125_135_140"/></setRelation></solitaryFeature></binaryRelation></solitaryFeature></binaryRelation><binaryRelation name="50"><cardinality max="1" min="1"/><solitaryFeature name="_r_1_4_121"><binaryRelation name="51"><cardinality max="1" min="1"/><solitaryFeature name="_r_1_4_121_141"><binaryRelation name="52"><cardinality max="1" min="1"/><solitaryFeature name="_r_1_4_121_141_142"/></binaryRelation></solitaryFeature></binaryRelation><binaryRelation name="53"><cardinality max="1" min="1"/><solitaryFeature name="_r_1_4_121_143"><binaryRelation name="54"><cardinality max="1" min="1"/><solitaryFeature name="_r_1_4_121_143_144"/></binaryRelation><binaryRelation name="55"><cardinality max="1" min="1"/><solitaryFeature name="_r_1_4_121_143_145"/></binaryRelation><binaryRelation name="56"><cardinality max="1" min="1"/><solitaryFeature name="_r_1_4_121_143_146"/></binaryRelation><binaryRelation name="57"><cardinality max="1" min="1"/><solitaryFeature name="_r_1_4_121_143_147"/></binaryRelation></solitaryFeature></binaryRelation><binaryRelation name="58"><cardinality max="1" min="1"/><solitaryFeature name="_r_1_4_121_148"><binaryRelation name="59"><cardinality max="1" min="1"/><solitaryFeature name="_r_1_4_121_148_149"/></binaryRelation><binaryRelation name="60"><cardinality max="1" min="1"/><solitaryFeature name="_r_1_4_121_148_150"/></binaryRelation></solitaryFeature></binaryRelation></solitaryFeature></binaryRelation><binaryRelation name="61"><cardinality max="1" min="1"/><solitaryFeature name="_r_1_4_122"/></binaryRelation></solitaryFeature></binaryRelation></solitaryFeature></binaryRelation></feature><requires feature="_r_1_2_5_8_9" name="constraint_8" requires="_r_1_4_120_125_135_137"/><requires feature="_r_1_2_5_8_25" name="constraint_10" requires="_r_1_4_121_141_142"/><requires feature="_r_1_2_5_8_26" name="constraint_9" requires="_r_1_4_120_125_135_140"/><requires feature="_r_1_2_5_8_9_17_35_36" name="constraint_11" requires="_r_1_4_120_123_126_131"/><requires feature="_r_1_2_5_8_9" name="constraint_6" requires="_r_1_4_120_123_126_128"/><requires feature="_r_1_2_5_8_9" name="constraint_7" requires="_r_1_4_120_123_126_131"/><requires feature="_r_1_2_5_8_9" name="constraint_5" requires="_r_1_4_120_123_126_127"/></feature-model>