<?xml version="1.0" encoding="UTF-8" standalone="no"?><feature-model xmlns:xsi="http://www.w3.org/2001/XMLSchema-instance" xsi:noNamespaceSchemaLocation="http://www.tdg-seville.info/benavides/featuremodelling/feature-model.xsd"><feature name="_r"><setRelation name="0"><cardinality max="5" min="1"/><groupedFeature name="_r_1_2"/><groupedFeature name="_r_1_5"/><groupedFeature name="_r_1_15"><binaryRelation name="1"><cardinality max="1" min="1"/><solitaryFeature name="_r_1_15_16"/></binaryRelation></groupedFeature><groupedFeature name="_r_1_21"/><groupedFeature name="_r_1_22"/></setRelation><binaryRelation name="2"><cardinality max="1" min="1"/><solitaryFeature name="_r_17"/></binaryRelation><setRelation name="3"><cardinality max="1" min="1"/><groupedFeature name="_r_18_19"/><groupedFeature name="_r_18_20"/></setRelation></feature></feature-model>